{
  "id": "khIQygcAgIWWNFNwf2JHnSir0Y22",
  "path": "users/khIQygcAgIWWNFNwf2JHnSir0Y22",
  "data": {
    "gradeLevel": 1,
    "hasGift": true,
    "lastLoginAt": {
      "__type__": "DatetimeWithNanoseconds",
      "value": "2026-02-13T07:33:31.007000+00:00"
    },
    "displayNameChangeCount": 0,
    "displayName": "아이돈노우",
    "photoURLChangeCount": 0,
    "postsCount": 1,
    "photoURL": "https://lh3.googleusercontent.com/a/ACg8ocLYeEbcbEQ2BKWV_i_GrphLmHoMXMPagT2K-EiQdTHkMg6xNfk=s96-c",
    "grade": "이코노미",
    "displayGrade": "이코노미 Lv.1",
    "hideBottomSheetAdUntil": {
      "__type__": "DatetimeWithNanoseconds",
      "value": "2026-04-19T02:10:38.722612+00:00"
    },
    "likesReceived": 0,
    "currentSkyEffect": null,
    "lastUpdatedAt": {
      "__type__": "DatetimeWithNanoseconds",
      "value": "2026-04-14T07:56:36.445000+00:00"
    },
    "followerCount": 0,
    "likesCount": 10,
    "displayNameEnable": true,
    "gradeUpdatedAt": {
      "__type__": "DatetimeWithNanoseconds",
      "value": "2025-11-01T05:46:55.079000+00:00"
    },
    "roles": [
      "user"
    ],
    "createdAt": {
      "__type__": "DatetimeWithNanoseconds",
      "value": "2025-11-01T05:46:55.079000+00:00"
    },
    "email": "jaewook9726@gmail.com",
    "followingCount": 0,
    "fcmToken": "cy-850R260ZGlusJ7OBr_6:APA91bERCiVi_Bhps_0AevqV-4lxwzMJow1wGDJhmzv4ATG0R-GVo1trXkFz5c40T-DJkXwCV0xrmPJhL5IB3hWOZpfTY6wkY8j1Gdi3pYEBPOy-xzA2ASw",
    "ownedEffects": [],
    "peanutCountLimit": 3,
    "peanutCount": 4,
    "uid": "khIQygcAgIWWNFNwf2JHnSir0Y22",
    "rankingAgreement": true,
    "photoURLEnable": true,
    "isBanned": false,
    "commentCount": 5,
    "joinedAt": {
      "__type__": "DatetimeWithNanoseconds",
      "value": "2025-11-01T05:46:55.079000+00:00"
    }
  },
  "subcollections": {
    "cards": [
      {
        "id": "airone",
        "path": "users/khIQygcAgIWWNFNwf2JHnSir0Y22/cards/airone",
        "data": {
          "checkPerMileKRW": 0,
          "memo": "에어원",
          "name": "신한",
          "creditPerMileKRW": 1000,
          "updatedAt": {
            "__type__": "DatetimeWithNanoseconds",
            "value": "2026-02-20T03:35:16.528000+00:00"
          }
        },
        "subcollections": {}
      },
      {
        "id": "lottecard_skypass",
        "path": "users/khIQygcAgIWWNFNwf2JHnSir0Y22/cards/lottecard_skypass",
        "data": {
          "checkPerMileKRW": 0,
          "memo": "롯스패",
          "name": "롯데",
          "creditPerMileKRW": 1000,
          "updatedAt": {
            "__type__": "DatetimeWithNanoseconds",
            "value": "2026-02-12T04:02:22.606000+00:00"
          }
        },
        "subcollections": {}
      },
      {
        "id": "samsung",
        "path": "users/khIQygcAgIWWNFNwf2JHnSir0Y22/cards/samsung",
        "data": {
          "checkPerMileKRW": 0,
          "memo": "삼앤마",
          "name": "삼성",
          "creditPerMileKRW": 1000,
          "updatedAt": {
            "__type__": "DatetimeWithNanoseconds",
            "value": "2026-02-20T03:58:43.053000+00:00"
          }
        },
        "subcollections": {}
      }
    ],
    "liked_posts": [
      {
        "id": "195d9662-9d78-4567-8e7f-cb55bdc65917",
        "path": "users/khIQygcAgIWWNFNwf2JHnSir0Y22/liked_posts/195d9662-9d78-4567-8e7f-cb55bdc65917",
        "data": {
          "likedAt": {
            "__type__": "DatetimeWithNanoseconds",
            "value": "2026-02-13T07:31:37.527000+00:00"
          },
          "title": "카카오페이 선물하기 투썸 케이크 기프티콘 25%",
          "postPath": "posts/20260201/posts/195d9662-9d78-4567-8e7f-cb55bdc65917"
        },
        "subcollections": {}
      },
      {
        "id": "1f5f8483-fa73-4c6c-a94b-509c0d969e94",
        "path": "users/khIQygcAgIWWNFNwf2JHnSir0Y22/liked_posts/1f5f8483-fa73-4c6c-a94b-509c0d969e94",
        "data": {
          "likedAt": {
            "__type__": "DatetimeWithNanoseconds",
            "value": "2026-02-13T07:31:40.658000+00:00"
          },
          "title": "게임온패스(46450원)",
          "postPath": "posts/20260131/posts/1f5f8483-fa73-4c6c-a94b-509c0d969e94"
        },
        "subcollections": {}
      },
      {
        "id": "3370e5e4-99ae-4486-a039-cddde4ccc3a1",
        "path": "users/khIQygcAgIWWNFNwf2JHnSir0Y22/liked_posts/3370e5e4-99ae-4486-a039-cddde4ccc3a1",
        "data": {
          "likedAt": {
            "__type__": "DatetimeWithNanoseconds",
            "value": "2026-02-13T07:32:01.408000+00:00"
          },
          "title": "돼지목살 1240원",
          "postPath": "posts/20260115/posts/3370e5e4-99ae-4486-a039-cddde4ccc3a1"
        },
        "subcollections": {}
      },
      {
        "id": "52e0668b-9f1c-4d17-8122-00eed7af26db",
        "path": "users/khIQygcAgIWWNFNwf2JHnSir0Y22/liked_posts/52e0668b-9f1c-4d17-8122-00eed7af26db",
        "data": {
          "likedAt": {
            "__type__": "DatetimeWithNanoseconds",
            "value": "2026-02-13T07:31:58.716000+00:00"
          },
          "title": "간만에 메가커피 23% 딜입니다.",
          "postPath": "posts/20260119/posts/52e0668b-9f1c-4d17-8122-00eed7af26db"
        },
        "subcollections": {}
      },
      {
        "id": "8ce30fe8-c449-4a2b-9b5a-bb0b5f16a25e",
        "path": "users/khIQygcAgIWWNFNwf2JHnSir0Y22/liked_posts/8ce30fe8-c449-4a2b-9b5a-bb0b5f16a25e",
        "data": {
          "likedAt": {
            "__type__": "DatetimeWithNanoseconds",
            "value": "2026-02-13T07:32:27.753000+00:00"
          },
          "title": "북라 지마켓 46500원 (5만원권)",
          "postPath": "posts/20260112/posts/8ce30fe8-c449-4a2b-9b5a-bb0b5f16a25e"
        },
        "subcollections": {}
      },
      {
        "id": "8e3a39ac-1980-4340-8c2b-1b039b59c719",
        "path": "users/khIQygcAgIWWNFNwf2JHnSir0Y22/liked_posts/8e3a39ac-1980-4340-8c2b-1b039b59c719",
        "data": {
          "likedAt": {
            "__type__": "DatetimeWithNanoseconds",
            "value": "2026-02-13T07:31:32.713000+00:00"
          },
          "title": "에어프랑스 에어로플랜 마일리지 100% 추가 적립 이벤트",
          "postPath": "posts/20260213/posts/8e3a39ac-1980-4340-8c2b-1b039b59c719"
        },
        "subcollections": {}
      },
      {
        "id": "bcc9d5c4-a958-4839-8f53-029146801e36",
        "path": "users/khIQygcAgIWWNFNwf2JHnSir0Y22/liked_posts/bcc9d5c4-a958-4839-8f53-029146801e36",
        "data": {
          "likedAt": {
            "__type__": "DatetimeWithNanoseconds",
            "value": "2026-02-13T07:31:35.373000+00:00"
          },
          "title": "신세계 3퍼 네이버",
          "postPath": "posts/20260210/posts/bcc9d5c4-a958-4839-8f53-029146801e36"
        },
        "subcollections": {}
      },
      {
        "id": "e00fcd1a-c021-49e7-8374-bca89ef7940b",
        "path": "users/khIQygcAgIWWNFNwf2JHnSir0Y22/liked_posts/e00fcd1a-c021-49e7-8374-bca89ef7940b",
        "data": {
          "likedAt": {
            "__type__": "DatetimeWithNanoseconds",
            "value": "2026-02-13T07:31:55.579000+00:00"
          },
          "title": "호텔럭스 그랜드하얏트 서울 방값무료;;;",
          "postPath": "posts/20260122/posts/e00fcd1a-c021-49e7-8374-bca89ef7940b"
        },
        "subcollections": {}
      },
      {
        "id": "ede089cf-a567-495c-84a3-621de6323cc9",
        "path": "users/khIQygcAgIWWNFNwf2JHnSir0Y22/liked_posts/ede089cf-a567-495c-84a3-621de6323cc9",
        "data": {
          "likedAt": {
            "__type__": "DatetimeWithNanoseconds",
            "value": "2026-02-13T07:31:43.332000+00:00"
          },
          "title": "현대, 북앤라이프 지마켓",
          "postPath": "posts/20260131/posts/ede089cf-a567-495c-84a3-621de6323cc9"
        },
        "subcollections": {}
      },
      {
        "id": "f6d1896a-4f3f-4226-bbf3-417e58aa9711",
        "path": "users/khIQygcAgIWWNFNwf2JHnSir0Y22/liked_posts/f6d1896a-4f3f-4226-bbf3-417e58aa9711",
        "data": {
          "likedAt": {
            "__type__": "DatetimeWithNanoseconds",
            "value": "2026-02-13T07:31:47.870000+00:00"
          },
          "title": "[CJ더마켓]스팸 340g 3개묶음 X 2 핫딜",
          "postPath": "posts/20260125/posts/f6d1896a-4f3f-4226-bbf3-417e58aa9711"
        },
        "subcollections": {}
      }
    ],
    "lots": [
      {
        "id": "lot_1762353361472",
        "path": "users/khIQygcAgIWWNFNwf2JHnSir0Y22/lots/lot_1762353361472",
        "data": {
          "status": "sold",
          "buyUnit": 97500,
          "qty": 1,
          "faceValue": 100000,
          "createdAt": {
            "__type__": "DatetimeWithNanoseconds",
            "value": "2025-11-05T14:36:01.510000+00:00"
          },
          "cardId": "lotte",
          "discount": 2.5,
          "buyDate": {
            "__type__": "DatetimeWithNanoseconds",
            "value": "2025-11-03T15:00:00+00:00"
          },
          "payType": "신용",
          "giftcardId": "shinsegae",
          "updatedAt": {
            "__type__": "DatetimeWithNanoseconds",
            "value": "2025-11-05T14:36:31.698000+00:00"
          }
        },
        "subcollections": {}
      },
      {
        "id": "lot_1770869100628",
        "path": "users/khIQygcAgIWWNFNwf2JHnSir0Y22/lots/lot_1770869100628",
        "data": {
          "trade": true,
          "updatedAt": {
            "__type__": "DatetimeWithNanoseconds",
            "value": "2026-02-12T04:05:28.366000+00:00"
          },
          "whereToBuyId": "gmarket",
          "status": "sold",
          "buyUnit": 487500,
          "faceValue": 500000,
          "qty": 1,
          "buyDate": {
            "__type__": "DatetimeWithNanoseconds",
            "value": "2026-01-31T15:00:00+00:00"
          },
          "memo": "",
          "discount": 2.5,
          "createdAt": {
            "__type__": "DatetimeWithNanoseconds",
            "value": "2026-02-12T04:05:00.680000+00:00"
          },
          "payType": "신용",
          "cardId": "lotte",
          "giftcardId": "shinsegae"
        },
        "subcollections": {}
      },
      {
        "id": "lot_1772366715560",
        "path": "users/khIQygcAgIWWNFNwf2JHnSir0Y22/lots/lot_1772366715560",
        "data": {
          "mileRuleUsedPerMileKRW": 1000,
          "status": "sold",
          "buyUnit": 96900,
          "qty": 1,
          "updatedAt": {
            "__type__": "DatetimeWithNanoseconds",
            "value": "2026-03-11T06:30:30.853000+00:00"
          },
          "buyDate": {
            "__type__": "DatetimeWithNanoseconds",
            "value": "2026-03-01T12:05:00.941012+00:00"
          },
          "giftcardId": "lotte",
          "memo": "",
          "createdAt": {
            "__type__": "DatetimeWithNanoseconds",
            "value": "2026-03-01T12:05:15.682000+00:00"
          },
          "cardId": "lottecard_skypass",
          "whereToBuyId": "thingshop",
          "trade": true,
          "faceValue": 100000,
          "miles": 97,
          "discount": 3.1,
          "payType": "신용"
        },
        "subcollections": {}
      },
      {
        "id": "lot_1772366735314",
        "path": "users/khIQygcAgIWWNFNwf2JHnSir0Y22/lots/lot_1772366735314",
        "data": {
          "mileRuleUsedPerMileKRW": 1000,
          "status": "sold",
          "buyUnit": 96900,
          "qty": 3,
          "updatedAt": {
            "__type__": "DatetimeWithNanoseconds",
            "value": "2026-03-11T06:30:42.361000+00:00"
          },
          "buyDate": {
            "__type__": "DatetimeWithNanoseconds",
            "value": "2026-03-01T12:05:17.802783+00:00"
          },
          "giftcardId": "lotte",
          "memo": "",
          "createdAt": {
            "__type__": "DatetimeWithNanoseconds",
            "value": "2026-03-01T12:05:35.476000+00:00"
          },
          "cardId": "lottecard_skypass",
          "whereToBuyId": "thingshop",
          "trade": true,
          "faceValue": 100000,
          "miles": 291,
          "discount": 3.1,
          "payType": "신용"
        },
        "subcollections": {}
      },
      {
        "id": "lot_1772366752575",
        "path": "users/khIQygcAgIWWNFNwf2JHnSir0Y22/lots/lot_1772366752575",
        "data": {
          "mileRuleUsedPerMileKRW": 1000,
          "status": "sold",
          "buyUnit": 96900,
          "qty": 3,
          "updatedAt": {
            "__type__": "DatetimeWithNanoseconds",
            "value": "2026-03-11T06:30:51.902000+00:00"
          },
          "buyDate": {
            "__type__": "DatetimeWithNanoseconds",
            "value": "2026-03-01T12:05:43.532374+00:00"
          },
          "giftcardId": "lotte",
          "memo": "",
          "createdAt": {
            "__type__": "DatetimeWithNanoseconds",
            "value": "2026-03-01T12:05:52.693000+00:00"
          },
          "cardId": "lottecard_skypass",
          "whereToBuyId": "thingshop",
          "trade": true,
          "faceValue": 100000,
          "miles": 291,
          "discount": 3.1,
          "payType": "신용"
        },
        "subcollections": {}
      },
      {
        "id": "lot_1772366780248",
        "path": "users/khIQygcAgIWWNFNwf2JHnSir0Y22/lots/lot_1772366780248",
        "data": {
          "mileRuleUsedPerMileKRW": 1000,
          "status": "sold",
          "buyUnit": 96900,
          "qty": 3,
          "updatedAt": {
            "__type__": "DatetimeWithNanoseconds",
            "value": "2026-03-11T06:31:01.742000+00:00"
          },
          "buyDate": {
            "__type__": "DatetimeWithNanoseconds",
            "value": "2026-03-01T12:06:11.954650+00:00"
          },
          "giftcardId": "lotte",
          "memo": "",
          "createdAt": {
            "__type__": "DatetimeWithNanoseconds",
            "value": "2026-03-01T12:06:20.372000+00:00"
          },
          "cardId": "lottecard_skypass",
          "whereToBuyId": "thingshop",
          "trade": true,
          "faceValue": 100000,
          "miles": 291,
          "discount": 3.1,
          "payType": "신용"
        },
        "subcollections": {}
      },
      {
        "id": "lot_1772441790684",
        "path": "users/khIQygcAgIWWNFNwf2JHnSir0Y22/lots/lot_1772441790684",
        "data": {
          "mileRuleUsedPerMileKRW": 1000,
          "status": "sold",
          "buyUnit": 97800,
          "qty": 10,
          "updatedAt": {
            "__type__": "DatetimeWithNanoseconds",
            "value": "2026-03-11T06:32:36.492000+00:00"
          },
          "buyDate": {
            "__type__": "DatetimeWithNanoseconds",
            "value": "2026-03-02T08:56:07.880115+00:00"
          },
          "giftcardId": "shinsegae",
          "memo": "",
          "createdAt": {
            "__type__": "DatetimeWithNanoseconds",
            "value": "2026-03-02T08:56:30.846000+00:00"
          },
          "cardId": "samsung",
          "whereToBuyId": "gmarket",
          "trade": true,
          "faceValue": 100000,
          "miles": 978,
          "discount": 2.2,
          "payType": "신용"
        },
        "subcollections": {}
      },
      {
        "id": "lot_1776153360880",
        "path": "users/khIQygcAgIWWNFNwf2JHnSir0Y22/lots/lot_1776153360880",
        "data": {
          "mileRuleUsedPerMileKRW": 1000,
          "status": "sold",
          "buyUnit": 97000,
          "qty": 2,
          "updatedAt": {
            "__type__": "DatetimeWithNanoseconds",
            "value": "2026-04-14T07:57:41.825000+00:00"
          },
          "buyDate": {
            "__type__": "DatetimeWithNanoseconds",
            "value": "2026-04-14T07:55:45.178006+00:00"
          },
          "giftcardId": "lotte",
          "memo": "",
          "createdAt": {
            "__type__": "DatetimeWithNanoseconds",
            "value": "2026-04-14T07:56:01.110000+00:00"
          },
          "cardId": "lottecard_skypass",
          "whereToBuyId": "thingshop",
          "trade": true,
          "faceValue": 500000,
          "miles": 194,
          "discount": 3.0,
          "payType": "신용"
        },
        "subcollections": {}
      }
    ],
    "my_comments": [
      {
        "id": "7UzK2IFXv9dESc97Dv5F",
        "path": "users/khIQygcAgIWWNFNwf2JHnSir0Y22/my_comments/7UzK2IFXv9dESc97Dv5F",
        "data": {
          "commentPath": "posts/20260210/posts/bcc9d5c4-a958-4839-8f53-029146801e36/comments/7UzK2IFXv9dESc97Dv5F",
          "createdAt": {
            "__type__": "DatetimeWithNanoseconds",
            "value": "2026-02-13T07:33:01.896000+00:00"
          },
          "postPath": "posts/20260210/posts/bcc9d5c4-a958-4839-8f53-029146801e36",
          "contentHtml": "<p>감사합니다</p>",
          "attachments": [],
          "contentType": "html"
        },
        "subcollections": {}
      },
      {
        "id": "CfzwUiSS84RiEtjJARzI",
        "path": "users/khIQygcAgIWWNFNwf2JHnSir0Y22/my_comments/CfzwUiSS84RiEtjJARzI",
        "data": {
          "commentPath": "posts/20260112/posts/8b5c7fef-4d9f-4496-8a04-c4e25d59f39f/comments/CfzwUiSS84RiEtjJARzI",
          "createdAt": {
            "__type__": "DatetimeWithNanoseconds",
            "value": "2026-01-13T15:02:55.628000+00:00"
          },
          "postPath": "posts/20260112/posts/8b5c7fef-4d9f-4496-8a04-c4e25d59f39f",
          "contentHtml": "<p>가지고 계시면 해야죠~^^</p>",
          "attachments": [],
          "contentType": "html"
        },
        "subcollections": {}
      },
      {
        "id": "WpF5Q7mYmoB65ZG1HvVF",
        "path": "users/khIQygcAgIWWNFNwf2JHnSir0Y22/my_comments/WpF5Q7mYmoB65ZG1HvVF",
        "data": {
          "commentPath": "posts/20260131/posts/1f5f8483-fa73-4c6c-a94b-509c0d969e94/comments/WpF5Q7mYmoB65ZG1HvVF",
          "createdAt": {
            "__type__": "DatetimeWithNanoseconds",
            "value": "2026-02-13T07:33:31.077000+00:00"
          },
          "postPath": "posts/20260131/posts/1f5f8483-fa73-4c6c-a94b-509c0d969e94",
          "contentHtml": "<p>감사합니다</p>",
          "attachments": [],
          "contentType": "html"
        },
        "subcollections": {}
      },
      {
        "id": "xCxTBPcsefOmcQ7OLBnc",
        "path": "users/khIQygcAgIWWNFNwf2JHnSir0Y22/my_comments/xCxTBPcsefOmcQ7OLBnc",
        "data": {
          "commentPath": "posts/20260112/posts/eb1f5ce9-16f3-4670-ad79-e2678e83493c/comments/xCxTBPcsefOmcQ7OLBnc",
          "createdAt": {
            "__type__": "DatetimeWithNanoseconds",
            "value": "2026-01-13T15:07:07.046000+00:00"
          },
          "postPath": "posts/20260112/posts/eb1f5ce9-16f3-4670-ad79-e2678e83493c",
          "contentHtml": "<p>반갑습니다~</p>",
          "attachments": [],
          "contentType": "html"
        },
        "subcollections": {}
      },
      {
        "id": "y3o8ADnJdtFOXbb4ogww",
        "path": "users/khIQygcAgIWWNFNwf2JHnSir0Y22/my_comments/y3o8ADnJdtFOXbb4ogww",
        "data": {
          "commentPath": "posts/20260201/posts/195d9662-9d78-4567-8e7f-cb55bdc65917/comments/y3o8ADnJdtFOXbb4ogww",
          "createdAt": {
            "__type__": "DatetimeWithNanoseconds",
            "value": "2026-02-13T07:33:23.124000+00:00"
          },
          "postPath": "posts/20260201/posts/195d9662-9d78-4567-8e7f-cb55bdc65917",
          "contentHtml": "<p>감사합니다</p>",
          "attachments": [],
          "contentType": "html"
        },
        "subcollections": {}
      }
    ],
    "my_posts": [
      {
        "id": "eabfb760-eec6-40f4-85d4-bf480b97def5",
        "path": "users/khIQygcAgIWWNFNwf2JHnSir0Y22/my_posts/eabfb760-eec6-40f4-85d4-bf480b97def5",
        "data": {
          "createdAt": {
            "__type__": "DatetimeWithNanoseconds",
            "value": "2025-12-04T04:39:12.083000+00:00"
          },
          "boardId": "deal",
          "postPath": "posts/20251204/posts/eabfb760-eec6-40f4-85d4-bf480b97def5",
          "title": "신백교환 5만원권 2%"
        },
        "subcollections": {}
      }
    ],
    "notifications": [
      {
        "id": "ElxiLHABApJNpJsIhqD9",
        "path": "users/khIQygcAgIWWNFNwf2JHnSir0Y22/notifications/ElxiLHABApJNpJsIhqD9",
        "data": {
          "commentedBy": "Lh7DTqqYVwNcB2bVkzhgEkLQXQS2",
          "boardName": "적립/카드 혜택",
          "isRead": true,
          "body": "라떼한잔님이 게시글에 댓글을 달았습니다.",
          "type": "post_comment",
          "commentId": "Lof1lxZrvjawRtp46WDE",
          "date": "20251204",
          "postTitle": "신백교환 5만원권 2%",
          "postId": "eabfb760-eec6-40f4-85d4-bf480b97def5",
          "boardId": "deal",
          "commentedByName": "라떼한잔",
          "path": "/community/detail/20251204/eabfb760-eec6-40f4-85d4-bf480b97def5",
          "title": "댓글 알림",
          "createdAt": {
            "__type__": "DatetimeWithNanoseconds",
            "value": "2025-12-04T05:41:15.348000+00:00"
          }
        },
        "subcollections": {}
      },
      {
        "id": "HXAQcYYOmPybovrf4tTY",
        "path": "users/khIQygcAgIWWNFNwf2JHnSir0Y22/notifications/HXAQcYYOmPybovrf4tTY",
        "data": {
          "boardName": "자유게시판",
          "likedBy": "aP3C0N511beyK7QZG9GyChs5oqO2",
          "body": "마일캐치님이 댓글에 좋아요를 하였습니다.",
          "isRead": true,
          "type": "comment_like",
          "commentId": "7UzK2IFXv9dESc97Dv5F",
          "date": "20260210",
          "createdAt": {
            "__type__": "DatetimeWithNanoseconds",
            "value": "2026-02-13T08:10:35.061000+00:00"
          },
          "postId": "bcc9d5c4-a958-4839-8f53-029146801e36",
          "boardId": "hotdeal",
          "commenterName": "아이돈노우",
          "path": "/community/detail/20260210/bcc9d5c4-a958-4839-8f53-029146801e36",
          "title": "댓글 좋아요 알림",
          "likedByName": "마일캐치"
        },
        "subcollections": {}
      },
      {
        "id": "p5LzcgLG0kD7oIIUvtsm",
        "path": "users/khIQygcAgIWWNFNwf2JHnSir0Y22/notifications/p5LzcgLG0kD7oIIUvtsm",
        "data": {
          "commentedBy": "aP3C0N511beyK7QZG9GyChs5oqO2",
          "boardName": "적립/카드 혜택",
          "isRead": true,
          "body": "마일캐치님이 게시글에 댓글을 달았습니다.",
          "type": "post_comment",
          "commentId": "jipCxsR8vISbQ79CiK4P",
          "date": "20251204",
          "postTitle": "신백교환 5만원권 2%",
          "postId": "eabfb760-eec6-40f4-85d4-bf480b97def5",
          "boardId": "deal",
          "commentedByName": "마일캐치",
          "path": "/community/detail/20251204/eabfb760-eec6-40f4-85d4-bf480b97def5",
          "title": "댓글 알림",
          "createdAt": {
            "__type__": "DatetimeWithNanoseconds",
            "value": "2025-12-04T05:14:10.111000+00:00"
          }
        },
        "subcollections": {}
      },
      {
        "id": "s2olxYxz6DWAMhiDGFJB",
        "path": "users/khIQygcAgIWWNFNwf2JHnSir0Y22/notifications/s2olxYxz6DWAMhiDGFJB",
        "data": {
          "boardName": "적립/카드 혜택",
          "likedBy": "AsiC7Pd78GfgNwUEHN1mfG7Nrkp2",
          "body": "킹스포드스미스국제공항님이 게시글에 좋아요를 하였습니다.",
          "isRead": true,
          "type": "post_like",
          "date": "20251204",
          "postTitle": "신백교환 5만원권 2%",
          "postId": "eabfb760-eec6-40f4-85d4-bf480b97def5",
          "boardId": "deal",
          "path": "/community/detail/20251204/eabfb760-eec6-40f4-85d4-bf480b97def5",
          "title": "좋아요 알림",
          "createdAt": {
            "__type__": "DatetimeWithNanoseconds",
            "value": "2025-12-04T16:28:46.326000+00:00"
          },
          "likedByName": "킹스포드스미스국제공항"
        },
        "subcollections": {}
      },
      {
        "id": "tleMhKIKCfnm0UtBrrwJ",
        "path": "users/khIQygcAgIWWNFNwf2JHnSir0Y22/notifications/tleMhKIKCfnm0UtBrrwJ",
        "data": {
          "boardName": "적립/카드 혜택",
          "likedBy": "aP3C0N511beyK7QZG9GyChs5oqO2",
          "body": "마일캐치님이 게시글에 좋아요를 하였습니다.",
          "isRead": true,
          "type": "post_like",
          "date": "20251204",
          "postTitle": "신백교환 5만원권 2%",
          "postId": "eabfb760-eec6-40f4-85d4-bf480b97def5",
          "boardId": "deal",
          "path": "/community/detail/20251204/eabfb760-eec6-40f4-85d4-bf480b97def5",
          "title": "좋아요 알림",
          "createdAt": {
            "__type__": "DatetimeWithNanoseconds",
            "value": "2025-12-04T05:13:46.238000+00:00"
          },
          "likedByName": "마일캐치"
        },
        "subcollections": {}
      },
      {
        "id": "vgNPlvOqWHdiuDugLMxY",
        "path": "users/khIQygcAgIWWNFNwf2JHnSir0Y22/notifications/vgNPlvOqWHdiuDugLMxY",
        "data": {
          "boardName": "적립/카드 혜택",
          "likedBy": "Lh7DTqqYVwNcB2bVkzhgEkLQXQS2",
          "body": "라떼한잔님이 게시글에 좋아요를 하였습니다.",
          "isRead": true,
          "type": "post_like",
          "date": "20251204",
          "postTitle": "신백교환 5만원권 2%",
          "postId": "eabfb760-eec6-40f4-85d4-bf480b97def5",
          "boardId": "deal",
          "path": "/community/detail/20251204/eabfb760-eec6-40f4-85d4-bf480b97def5",
          "title": "좋아요 알림",
          "createdAt": {
            "__type__": "DatetimeWithNanoseconds",
            "value": "2025-12-04T05:41:05.238000+00:00"
          },
          "likedByName": "라떼한잔"
        },
        "subcollections": {}
      }
    ],
    "peanut_history": [
      {
        "id": "6625KXuU18oxPkgAcRsv",
        "path": "users/khIQygcAgIWWNFNwf2JHnSir0Y22/peanut_history/6625KXuU18oxPkgAcRsv",
        "data": {
          "postTitle": "게임온패스(46450원)",
          "postId": "1f5f8483-fa73-4c6c-a94b-509c0d969e94",
          "amount": 1,
          "boardId": "hotdeal",
          "dateString": "20260131",
          "type": "post_like",
          "createdAt": {
            "__type__": "DatetimeWithNanoseconds",
            "value": "2026-02-13T07:31:40.624000+00:00"
          }
        },
        "subcollections": {}
      },
      {
        "id": "8ueHglPQUxy3zQoqFIwY",
        "path": "users/khIQygcAgIWWNFNwf2JHnSir0Y22/peanut_history/8ueHglPQUxy3zQoqFIwY",
        "data": {
          "postTitle": "카카오페이 선물하기 투썸 케이크 기프티콘 25%",
          "postId": "195d9662-9d78-4567-8e7f-cb55bdc65917",
          "amount": 2,
          "dateString": "20260201",
          "createdAt": {
            "__type__": "DatetimeWithNanoseconds",
            "value": "2026-02-13T07:33:23.245000+00:00"
          },
          "type": "comment_create",
          "commentId": "y3o8ADnJdtFOXbb4ogww"
        },
        "subcollections": {}
      },
      {
        "id": "GPEE7js6WNUhdTeGPp2V",
        "path": "users/khIQygcAgIWWNFNwf2JHnSir0Y22/peanut_history/GPEE7js6WNUhdTeGPp2V",
        "data": {
          "postTitle": "상테크 시작",
          "postId": "8b5c7fef-4d9f-4496-8a04-c4e25d59f39f",
          "amount": 2,
          "dateString": "20260112",
          "createdAt": {
            "__type__": "DatetimeWithNanoseconds",
            "value": "2026-01-13T15:02:55.751000+00:00"
          },
          "type": "comment_create",
          "commentId": "CfzwUiSS84RiEtjJARzI"
        },
        "subcollections": {}
      },
      {
        "id": "MoFqdYtqCBLDU8FsLd8W",
        "path": "users/khIQygcAgIWWNFNwf2JHnSir0Y22/peanut_history/MoFqdYtqCBLDU8FsLd8W",
        "data": {
          "postTitle": "카카오페이 선물하기 투썸 케이크 기프티콘 25%",
          "postId": "195d9662-9d78-4567-8e7f-cb55bdc65917",
          "amount": 1,
          "boardId": "hotdeal",
          "dateString": "20260201",
          "type": "post_like",
          "createdAt": {
            "__type__": "DatetimeWithNanoseconds",
            "value": "2026-02-13T07:31:37.504000+00:00"
          }
        },
        "subcollections": {}
      },
      {
        "id": "N1Y7iabxVwT6zg9bG41X",
        "path": "users/khIQygcAgIWWNFNwf2JHnSir0Y22/peanut_history/N1Y7iabxVwT6zg9bG41X",
        "data": {
          "postTitle": "신백교환 5만원권 2%",
          "postId": "eabfb760-eec6-40f4-85d4-bf480b97def5",
          "amount": 10,
          "boardId": "deal",
          "dateString": "20251204",
          "type": "post_create",
          "createdAt": {
            "__type__": "DatetimeWithNanoseconds",
            "value": "2025-12-04T04:39:12.203000+00:00"
          }
        },
        "subcollections": {}
      },
      {
        "id": "NEXoVtoSEnmv1Div9y18",
        "path": "users/khIQygcAgIWWNFNwf2JHnSir0Y22/peanut_history/NEXoVtoSEnmv1Div9y18",
        "data": {
          "postTitle": "신세계 3퍼 네이버",
          "postId": "bcc9d5c4-a958-4839-8f53-029146801e36",
          "amount": 2,
          "dateString": "20260210",
          "createdAt": {
            "__type__": "DatetimeWithNanoseconds",
            "value": "2026-02-13T07:33:02.019000+00:00"
          },
          "type": "comment_create",
          "commentId": "7UzK2IFXv9dESc97Dv5F"
        },
        "subcollections": {}
      },
      {
        "id": "QMMol3pHL5TFBjqywteM",
        "path": "users/khIQygcAgIWWNFNwf2JHnSir0Y22/peanut_history/QMMol3pHL5TFBjqywteM",
        "data": {
          "postTitle": "북라 지마켓 46500원 (5만원권)",
          "postId": "8ce30fe8-c449-4a2b-9b5a-bb0b5f16a25e",
          "amount": 1,
          "boardId": "hotdeal",
          "dateString": "20260112",
          "type": "post_like",
          "createdAt": {
            "__type__": "DatetimeWithNanoseconds",
            "value": "2026-02-13T07:32:27.724000+00:00"
          }
        },
        "subcollections": {}
      },
      {
        "id": "UcN2nBCyB8VNqjIjissn",
        "path": "users/khIQygcAgIWWNFNwf2JHnSir0Y22/peanut_history/UcN2nBCyB8VNqjIjissn",
        "data": {
          "postTitle": "호텔럭스 그랜드하얏트 서울 방값무료;;;",
          "postId": "e00fcd1a-c021-49e7-8374-bca89ef7940b",
          "amount": 1,
          "boardId": "hotdeal",
          "dateString": "20260122",
          "type": "post_like",
          "createdAt": {
            "__type__": "DatetimeWithNanoseconds",
            "value": "2026-02-13T07:31:55.549000+00:00"
          }
        },
        "subcollections": {}
      },
      {
        "id": "Xti5Prt2kdROV8a8a9cl",
        "path": "users/khIQygcAgIWWNFNwf2JHnSir0Y22/peanut_history/Xti5Prt2kdROV8a8a9cl",
        "data": {
          "postTitle": "에어프랑스 에어로플랜 마일리지 100% 추가 적립 이벤트",
          "postId": "8e3a39ac-1980-4340-8c2b-1b039b59c719",
          "amount": 1,
          "boardId": "hotdeal",
          "dateString": "20260213",
          "type": "post_like",
          "createdAt": {
            "__type__": "DatetimeWithNanoseconds",
            "value": "2026-02-13T07:31:32.666000+00:00"
          }
        },
        "subcollections": {}
      },
      {
        "id": "asWJxoooMnuWbXfCQfHM",
        "path": "users/khIQygcAgIWWNFNwf2JHnSir0Y22/peanut_history/asWJxoooMnuWbXfCQfHM",
        "data": {
          "postTitle": "신세계 3퍼 네이버",
          "postId": "bcc9d5c4-a958-4839-8f53-029146801e36",
          "amount": 1,
          "boardId": "hotdeal",
          "dateString": "20260210",
          "type": "post_like",
          "createdAt": {
            "__type__": "DatetimeWithNanoseconds",
            "value": "2026-02-13T07:31:35.344000+00:00"
          }
        },
        "subcollections": {}
      },
      {
        "id": "dw8erwa5myKVyAYUMWS9",
        "path": "users/khIQygcAgIWWNFNwf2JHnSir0Y22/peanut_history/dw8erwa5myKVyAYUMWS9",
        "data": {
          "postTitle": "간만에 메가커피 23% 딜입니다.",
          "postId": "52e0668b-9f1c-4d17-8122-00eed7af26db",
          "amount": 1,
          "boardId": "hotdeal",
          "dateString": "20260119",
          "type": "post_like",
          "createdAt": {
            "__type__": "DatetimeWithNanoseconds",
            "value": "2026-02-13T07:31:58.691000+00:00"
          }
        },
        "subcollections": {}
      },
      {
        "id": "dwEbmhrR5gesZ4aZH6VF",
        "path": "users/khIQygcAgIWWNFNwf2JHnSir0Y22/peanut_history/dwEbmhrR5gesZ4aZH6VF",
        "data": {
          "postTitle": "게임온패스(46450원)",
          "postId": "1f5f8483-fa73-4c6c-a94b-509c0d969e94",
          "amount": 2,
          "dateString": "20260131",
          "createdAt": {
            "__type__": "DatetimeWithNanoseconds",
            "value": "2026-02-13T07:33:31.175000+00:00"
          },
          "type": "comment_create",
          "commentId": "WpF5Q7mYmoB65ZG1HvVF"
        },
        "subcollections": {}
      },
      {
        "id": "qtZ3uWtROOWRFN3b3CQy",
        "path": "users/khIQygcAgIWWNFNwf2JHnSir0Y22/peanut_history/qtZ3uWtROOWRFN3b3CQy",
        "data": {
          "postTitle": "돼지목살 1240원",
          "postId": "3370e5e4-99ae-4486-a039-cddde4ccc3a1",
          "amount": 1,
          "boardId": "hotdeal",
          "dateString": "20260115",
          "type": "post_like",
          "createdAt": {
            "__type__": "DatetimeWithNanoseconds",
            "value": "2026-02-13T07:32:01.378000+00:00"
          }
        },
        "subcollections": {}
      },
      {
        "id": "rQK0YIJ4LJvEUeyxpH5T",
        "path": "users/khIQygcAgIWWNFNwf2JHnSir0Y22/peanut_history/rQK0YIJ4LJvEUeyxpH5T",
        "data": {
          "postTitle": "[CJ더마켓]스팸 340g 3개묶음 X 2 핫딜",
          "postId": "f6d1896a-4f3f-4226-bbf3-417e58aa9711",
          "amount": 1,
          "boardId": "hotdeal",
          "dateString": "20260125",
          "type": "post_like",
          "createdAt": {
            "__type__": "DatetimeWithNanoseconds",
            "value": "2026-02-13T07:31:47.843000+00:00"
          }
        },
        "subcollections": {}
      },
      {
        "id": "rdUAV3jyTjY3auGp34lN",
        "path": "users/khIQygcAgIWWNFNwf2JHnSir0Y22/peanut_history/rdUAV3jyTjY3auGp34lN",
        "data": {
          "postTitle": "반갑습니다",
          "postId": "eb1f5ce9-16f3-4670-ad79-e2678e83493c",
          "amount": 2,
          "dateString": "20260112",
          "createdAt": {
            "__type__": "DatetimeWithNanoseconds",
            "value": "2026-01-13T15:07:07.176000+00:00"
          },
          "type": "comment_create",
          "commentId": "xCxTBPcsefOmcQ7OLBnc"
        },
        "subcollections": {}
      },
      {
        "id": "zY3NaaTLIhtw2kvKBCVH",
        "path": "users/khIQygcAgIWWNFNwf2JHnSir0Y22/peanut_history/zY3NaaTLIhtw2kvKBCVH",
        "data": {
          "postTitle": "현대, 북앤라이프 지마켓",
          "postId": "ede089cf-a567-495c-84a3-621de6323cc9",
          "amount": 1,
          "boardId": "hotdeal",
          "dateString": "20260131",
          "type": "post_like",
          "createdAt": {
            "__type__": "DatetimeWithNanoseconds",
            "value": "2026-02-13T07:31:43.304000+00:00"
          }
        },
        "subcollections": {}
      }
    ],
    "sales": [
      {
        "id": "sale_1762353391632",
        "path": "users/khIQygcAgIWWNFNwf2JHnSir0Y22/sales/sale_1762353391632",
        "data": {
          "sellTotal": 97000,
          "profit": -500,
          "updatedAt": {
            "__type__": "DatetimeWithNanoseconds",
            "value": "2025-11-05T14:36:31.668000+00:00"
          },
          "mileRuleUsedPerMileKRW": 1000,
          "sellUnit": 97000,
          "lotId": "lot_1762353361472",
          "createdAt": {
            "__type__": "DatetimeWithNanoseconds",
            "value": "2025-11-05T14:36:31.668000+00:00"
          },
          "sellDate": {
            "__type__": "DatetimeWithNanoseconds",
            "value": "2025-11-03T15:00:00+00:00"
          },
          "costPerMile": 5.1,
          "discount": 3.0,
          "buyTotal": 97500,
          "qty": 1,
          "miles": 98
        },
        "subcollections": {}
      },
      {
        "id": "sale_1770869128304",
        "path": "users/khIQygcAgIWWNFNwf2JHnSir0Y22/sales/sale_1770869128304",
        "data": {
          "branchId": "mirae",
          "sellTotal": 485000,
          "profit": -2500,
          "updatedAt": {
            "__type__": "DatetimeWithNanoseconds",
            "value": "2026-02-12T04:05:28.320000+00:00"
          },
          "mileRuleUsedPerMileKRW": 1000,
          "sellUnit": 485000,
          "lotId": "lot_1770869100628",
          "createdAt": {
            "__type__": "DatetimeWithNanoseconds",
            "value": "2026-02-12T04:05:28.320000+00:00"
          },
          "sellDate": {
            "__type__": "DatetimeWithNanoseconds",
            "value": "2026-02-09T15:00:00+00:00"
          },
          "costPerMile": 5.12,
          "discount": 3.0,
          "buyTotal": 487500,
          "qty": 1,
          "miles": 488
        },
        "subcollections": {}
      },
      {
        "id": "sale_1773210630714",
        "path": "users/khIQygcAgIWWNFNwf2JHnSir0Y22/sales/sale_1773210630714",
        "data": {
          "branchId": "mirae",
          "sellTotal": 96600,
          "profit": -300,
          "updatedAt": {
            "__type__": "DatetimeWithNanoseconds",
            "value": "2026-03-11T06:30:30.771000+00:00"
          },
          "mileRuleUsedPerMileKRW": 1000,
          "sellUnit": 96600,
          "lotId": "lot_1772366715560",
          "createdAt": {
            "__type__": "DatetimeWithNanoseconds",
            "value": "2026-03-11T06:30:30.771000+00:00"
          },
          "sellDate": {
            "__type__": "DatetimeWithNanoseconds",
            "value": "2026-03-11T06:30:16.076344+00:00"
          },
          "costPerMile": 3.09,
          "discount": 3.4,
          "buyTotal": 96900,
          "qty": 1,
          "miles": 97
        },
        "subcollections": {}
      },
      {
        "id": "sale_1773210642239",
        "path": "users/khIQygcAgIWWNFNwf2JHnSir0Y22/sales/sale_1773210642239",
        "data": {
          "branchId": "mirae",
          "sellTotal": 289800,
          "profit": -900,
          "updatedAt": {
            "__type__": "DatetimeWithNanoseconds",
            "value": "2026-03-11T06:30:42.292000+00:00"
          },
          "mileRuleUsedPerMileKRW": 1000,
          "sellUnit": 96600,
          "lotId": "lot_1772366735314",
          "createdAt": {
            "__type__": "DatetimeWithNanoseconds",
            "value": "2026-03-11T06:30:42.292000+00:00"
          },
          "sellDate": {
            "__type__": "DatetimeWithNanoseconds",
            "value": "2026-03-11T06:30:33.296530+00:00"
          },
          "costPerMile": 3.09,
          "discount": 3.4,
          "buyTotal": 290700,
          "qty": 3,
          "miles": 291
        },
        "subcollections": {}
      },
      {
        "id": "sale_1773210651786",
        "path": "users/khIQygcAgIWWNFNwf2JHnSir0Y22/sales/sale_1773210651786",
        "data": {
          "branchId": "mirae",
          "sellTotal": 289800,
          "profit": -900,
          "updatedAt": {
            "__type__": "DatetimeWithNanoseconds",
            "value": "2026-03-11T06:30:51.852000+00:00"
          },
          "mileRuleUsedPerMileKRW": 1000,
          "sellUnit": 96600,
          "lotId": "lot_1772366752575",
          "createdAt": {
            "__type__": "DatetimeWithNanoseconds",
            "value": "2026-03-11T06:30:51.852000+00:00"
          },
          "sellDate": {
            "__type__": "DatetimeWithNanoseconds",
            "value": "2026-03-11T06:30:44.240519+00:00"
          },
          "costPerMile": 3.09,
          "discount": 3.4,
          "buyTotal": 290700,
          "qty": 3,
          "miles": 291
        },
        "subcollections": {}
      },
      {
        "id": "sale_1773210661635",
        "path": "users/khIQygcAgIWWNFNwf2JHnSir0Y22/sales/sale_1773210661635",
        "data": {
          "branchId": "mirae",
          "sellTotal": 289800,
          "profit": -900,
          "updatedAt": {
            "__type__": "DatetimeWithNanoseconds",
            "value": "2026-03-11T06:31:01.692000+00:00"
          },
          "mileRuleUsedPerMileKRW": 1000,
          "sellUnit": 96600,
          "lotId": "lot_1772366780248",
          "createdAt": {
            "__type__": "DatetimeWithNanoseconds",
            "value": "2026-03-11T06:31:01.692000+00:00"
          },
          "sellDate": {
            "__type__": "DatetimeWithNanoseconds",
            "value": "2026-03-11T06:30:54.208805+00:00"
          },
          "costPerMile": 3.09,
          "discount": 3.4,
          "buyTotal": 290700,
          "qty": 3,
          "miles": 291
        },
        "subcollections": {}
      },
      {
        "id": "sale_1773210756311",
        "path": "users/khIQygcAgIWWNFNwf2JHnSir0Y22/sales/sale_1773210756311",
        "data": {
          "branchId": "mirae",
          "sellTotal": 968000,
          "profit": -10000,
          "updatedAt": {
            "__type__": "DatetimeWithNanoseconds",
            "value": "2026-03-11T06:32:36.422000+00:00"
          },
          "mileRuleUsedPerMileKRW": 1000,
          "sellUnit": 96800,
          "lotId": "lot_1772441790684",
          "createdAt": {
            "__type__": "DatetimeWithNanoseconds",
            "value": "2026-03-11T06:32:36.422000+00:00"
          },
          "sellDate": {
            "__type__": "DatetimeWithNanoseconds",
            "value": "2026-03-11T06:31:03.127092+00:00"
          },
          "costPerMile": 10.22,
          "discount": 3.2,
          "buyTotal": 978000,
          "qty": 10,
          "miles": 978
        },
        "subcollections": {}
      },
      {
        "id": "sale_1776153461604",
        "path": "users/khIQygcAgIWWNFNwf2JHnSir0Y22/sales/sale_1776153461604",
        "data": {
          "branchId": "mirae",
          "sellTotal": 966000,
          "profit": 772000,
          "updatedAt": {
            "__type__": "DatetimeWithNanoseconds",
            "value": "2026-04-14T07:57:41.729000+00:00"
          },
          "mileRuleUsedPerMileKRW": 1000,
          "sellUnit": 483000,
          "lotId": "lot_1776153360880",
          "createdAt": {
            "__type__": "DatetimeWithNanoseconds",
            "value": "2026-04-14T07:57:41.729000+00:00"
          },
          "sellDate": {
            "__type__": "DatetimeWithNanoseconds",
            "value": "2026-04-14T07:56:49.940461+00:00"
          },
          "costPerMile": -3979.38,
          "discount": 3.4,
          "buyTotal": 194000,
          "qty": 2,
          "miles": 194
        },
        "subcollections": {}
      }
    ],
    "where_to_buy": [
      {
        "id": "gmarket",
        "path": "users/khIQygcAgIWWNFNwf2JHnSir0Y22/where_to_buy/gmarket",
        "data": {
          "memo": null,
          "name": "지마켓",
          "updatedAt": {
            "__type__": "DatetimeWithNanoseconds",
            "value": "2026-02-12T04:01:45.178000+00:00"
          }
        },
        "subcollections": {}
      },
      {
        "id": "thingshop",
        "path": "users/khIQygcAgIWWNFNwf2JHnSir0Y22/where_to_buy/thingshop",
        "data": {
          "memo": null,
          "name": "띵샵",
          "updatedAt": {
            "__type__": "DatetimeWithNanoseconds",
            "value": "2026-03-01T12:04:58.832000+00:00"
          }
        },
        "subcollections": {}
      }
    ]
  },
  "backupMeta": {
    "userId": "khIQygcAgIWWNFNwf2JHnSir0Y22",
    "safeFileName": "khIQygcAgIWWNFNwf2JHnSir0Y22.json"
  }
}